karrio/mappers/laposte/__init__.py
karrio/mappers/laposte/mapper.py
karrio/mappers/laposte/proxy.py
karrio/mappers/laposte/settings.py
karrio/plugins/laposte/__init__.py
karrio/providers/laposte/__init__.py
karrio/providers/laposte/error.py
karrio/providers/laposte/tracking.py
karrio/providers/laposte/units.py
karrio/providers/laposte/utils.py
karrio/schemas/laposte/__init__.py
karrio/schemas/laposte/error.py
karrio/schemas/laposte/tracking_response.py
karrio_laposte-2026.1.4.dist-info/METADATA
karrio_laposte-2026.1.4.dist-info/WHEEL
karrio_laposte-2026.1.4.dist-info/entry_points.txt
karrio_laposte-2026.1.4.dist-info/top_level.txt
karrio_laposte-2026.1.4.dist-info/RECORD
